Metadata-Version: 2.1
Name: readify
Version: 1.0.0
Summary: Convert Integer to Human Readable format
Home-page: https://yoginth.com
Author: Yoginth
Author-email: me@yoginth.com
Maintainer: Yoginth
Maintainer-email: me@yoginth.com
License: MIT
Project-URL: Source, https://gitlab.com/yoginth/readify
Keywords: Humanize,Readable
Platform: UNKNOWN
Classifier: Programming Language :: Python
Classifier: Natural Language :: English
Classifier: Environment :: Plugins
Classifier: Operating System :: OS Independent
Classifier: Intended Audience :: Developers
Classifier: License :: OSI Approved :: MIT License
